<annotation verified="yes">
	<folder>tu2</folder>
	<filename>image013-00382.jpg</filename>
	<path>D:\tu2\image013-00382.jpg</path>
	<source>
		<database>Unknown</database>
	</source>
	<size>
		<width>1080</width>
		<height>1080</height>
		<depth>3</depth>
	</size>
	<segmented>0</segmented>
	<object>
		<name>smoke</name>
		<pose>Unspecified</pose>
		<truncated>0</truncated>
		<difficult>0</difficult>
		<robndbox>
			<cx>733.3333</cx>
			<cy>223.5556</cy>
			<w>656.0</w>
			<h>378.0</h>
			<angle>0.04</angle>
		</robndbox>
		<extra/>
	</object>
	<object>
		<name>smoke</name>
		<pose>Unspecified</pose>
		<truncated>0</truncated>
		<difficult>0</difficult>
		<robndbox>
			<cx>936.6667</cx>
			<cy>537.925</cy>
			<w>264.6667</w>
			<h>198.7389</h>
			<angle>0.03</angle>
		</robndbox>
		<extra/>
	</object>
</annotation>
