<annotation verified="yes">
	<folder>tu2</folder>
	<filename>image013-00319.jpg</filename>
	<path>D:\tu2\image013-00319.jpg</path>
	<source>
		<database>Unknown</database>
	</source>
	<size>
		<width>1080</width>
		<height>1080</height>
		<depth>3</depth>
	</size>
	<segmented>0</segmented>
	<object>
		<name>smoke</name>
		<pose>Unspecified</pose>
		<truncated>0</truncated>
		<difficult>0</difficult>
		<robndbox>
			<cx>688.8333</cx>
			<cy>117.0556</cy>
			<w>703.0</w>
			<h>183.0</h>
			<angle>0.03</angle>
		</robndbox>
		<extra/>
	</object>
	<object>
		<name>smoke</name>
		<pose>Unspecified</pose>
		<truncated>0</truncated>
		<difficult>0</difficult>
		<robndbox>
			<cx>899.3333</cx>
			<cy>316.0556</cy>
			<w>264.0</w>
			<h>147.0</h>
			<angle>0.06</angle>
		</robndbox>
		<extra/>
	</object>
	<object>
		<name>smoke</name>
		<pose>Unspecified</pose>
		<truncated>0</truncated>
		<difficult>0</difficult>
		<robndbox>
			<cx>253.3333</cx>
			<cy>466.5556</cy>
			<w>258.0</w>
			<h>496.0</h>
			<angle>0.43</angle>
		</robndbox>
		<extra/>
	</object>
	<object>
		<name>smoke</name>
		<pose>Unspecified</pose>
		<truncated>0</truncated>
		<difficult>0</difficult>
		<robndbox>
			<cx>587.3333</cx>
			<cy>802.0556</cy>
			<w>234.0</w>
			<h>311.0</h>
			<angle>0.0</angle>
		</robndbox>
		<extra/>
	</object>
</annotation>
